plex_music_ratings_sync/__init__.py
plex_music_ratings_sync/__main__.py
plex_music_ratings_sync/cli.py
plex_music_ratings_sync/config.py
plex_music_ratings_sync/config.template.yml
plex_music_ratings_sync/lock.py
plex_music_ratings_sync/logger.py
plex_music_ratings_sync/ratings.py
plex_music_ratings_sync/state.py
plex_music_ratings_sync/sync.py
plex_music_ratings_sync/util/datetime.py
plex_music_ratings_sync/util/paths.py
plexmusicratingssync-2.0.0.dist-info/licenses/LICENSE
plexmusicratingssync-2.0.0.dist-info/METADATA
plexmusicratingssync-2.0.0.dist-info/WHEEL
plexmusicratingssync-2.0.0.dist-info/entry_points.txt
plexmusicratingssync-2.0.0.dist-info/top_level.txt
plexmusicratingssync-2.0.0.dist-info/RECORD
