Metadata-Version: 2.4
Name: PlexMusicRatingsSync
Version: 2.0.0
Summary: PlexMusicRatingsSync keeps your Plex music ratings in sync with your audio files.
Author-email: Ricardo Amaral <hello@ricardoamaral.net>
License: The MIT License (MIT)
Project-URL: Repository, https://github.com/rfgamaral/PlexMusicRatingsSync
Project-URL: Issues, https://github.com/rfgamaral/PlexMusicRatingsSync/issues
Project-URL: Changelog, https://github.com/rfgamaral/PlexMusicRatingsSync/blob/main/CHANGELOG.md
Classifier: Environment :: Console
Classifier: Operating System :: OS Independent
Classifier: License :: OSI Approved :: MIT License
Classifier: Programming Language :: Python :: 3
Requires-Python: >=3.9
License-File: LICENSE
Requires-Dist: click==8.1.8
Requires-Dist: colorama==0.4.6
Requires-Dist: filelock==3.17.0
Requires-Dist: mutagen==1.47.0
Requires-Dist: platformdirs==4.3.6
Requires-Dist: plexapi==4.16.1
Requires-Dist: pyyaml==6.0.2
Dynamic: license-file
